{"frames": {

"dogwalk1.png":
{
	"frame": {"x":2,"y":2,"w":63,"h":47},
	"rotated": false,
	"trimmed": true,
	"spriteSourceSize": {"x":1,"y":12,"w":63,"h":47},
	"sourceSize": {"w":64,"h":64},
	"pivot": {"x":0.5,"y":0.5}
},
"dogwalk2.png":
{
	"frame": {"x":67,"y":2,"w":63,"h":47},
	"rotated": false,
	"trimmed": true,
	"spriteSourceSize": {"x":1,"y":13,"w":63,"h":47},
	"sourceSize": {"w":64,"h":64},
	"pivot": {"x":0.5,"y":0.5}
},
"dogwalk3.png":
{
	"frame": {"x":132,"y":2,"w":63,"h":47},
	"rotated": false,
	"trimmed": true,
	"spriteSourceSize": {"x":1,"y":13,"w":63,"h":47},
	"sourceSize": {"w":64,"h":64},
	"pivot": {"x":0.5,"y":0.5}
},
"dogwalk4.png":
{
	"frame": {"x":67,"y":2,"w":63,"h":47},
	"rotated": false,
	"trimmed": true,
	"spriteSourceSize": {"x":1,"y":13,"w":63,"h":47},
	"sourceSize": {"w":64,"h":64},
	"pivot": {"x":0.5,"y":0.5}
}},
"meta": {
	"app": "http://www.codeandweb.com/texturepacker",
	"version": "1.0",
	"image": "dogwalk.png",
	"format": "RGBA8888",
	"size": {"w":197,"h":51},
	"scale": "1",
	"smartupdate": "$TexturePacker:SmartUpdate:0480b3d726dad62f5bd8d8df023661eb:42e89ef3150bff2d9c4350b044616644:cb0dfaa645e0d659a7bf7cc3020fc029$"
}
}
